{"chunk_definitions":[{"row":41,"row_count":1,"visible":true,"expansion_state":0,"options":{"engine":"r","label":"unnamed-chunk-106"},"document_id":"9AEDA2A1","chunk_id":"cgpbob1d1bqco","chunk_label":"unnamed-chunk-2"},{"row":51,"row_count":1,"visible":true,"expansion_state":0,"options":{"engine":"r","label":"unnamed-chunk-107"},"document_id":"9AEDA2A1","chunk_id":"cdc9hknav2ybt","chunk_label":"unnamed-chunk-3"},{"row":64,"row_count":1,"visible":true,"expansion_state":0,"options":{"engine":"r","label":"unnamed-chunk-108"},"document_id":"9AEDA2A1","chunk_id":"cijniceedvwdn","chunk_label":"unnamed-chunk-4"},{"row":75,"row_count":1,"visible":true,"expansion_state":0,"options":{"engine":"r","label":"unnamed-chunk-119"},"document_id":"9AEDA2A1","chunk_id":"cxka2l3o0maf7","chunk_label":"unnamed-chunk-5"},{"row":86,"row_count":1,"visible":true,"expansion_state":0,"options":{"engine":"r","label":"unnamed-chunk-120"},"document_id":"9AEDA2A1","chunk_id":"crnwi7aw0njw2","chunk_label":"unnamed-chunk-6"}],"doc_write_time":1664910419}